search_package/__init__.py
search_package/search.py
search_terminal-0.0.2.dist-info/METADATA
search_terminal-0.0.2.dist-info/WHEEL
search_terminal-0.0.2.dist-info/entry_points.txt
search_terminal-0.0.2.dist-info/top_level.txt
search_terminal-0.0.2.dist-info/RECORD
