Metadata-Version: 2.1
Name: search-terminal
Version: 0.0.2
Summary: This is a program that allows you to search the web from the comfort of your terminal.
Home-page: https://github.com/Dr-GameDev/Google-Search-Package
Author: Babalo Majiyezi
Author-email: raymondbabalo5@gmail.com
License: MIT
Keywords: search,web search,terminal search
Classifier: Programming Language :: Python :: 3
Classifier: License :: OSI Approved :: MIT License
Classifier: Operating System :: OS Independent
Requires-Python: >=3.6
Requires-Dist: argparse
Requires-Dist: requests
Requires-Dist: html2text
